[{"name":"abstract fun addEnchantment(enchantment: Enchantment): GuiButton","description":"eu.xap3y.xagui.interfaces.GuiButtonInterface.addEnchantment","location":"-xa-gui/eu.xap3y.xagui.interfaces/-gui-button-interface/add-enchantment.html","searchKeys":["addEnchantment","abstract fun addEnchantment(enchantment: Enchantment): GuiButton","eu.xap3y.xagui.interfaces.GuiButtonInterface.addEnchantment"]},{"name":"abstract fun addEnchantment(enchantment: Enchantment, level: Int): GuiButton","description":"eu.xap3y.xagui.interfaces.GuiButtonInterface.addEnchantment","location":"-xa-gui/eu.xap3y.xagui.interfaces/-gui-button-interface/add-enchantment.html","searchKeys":["addEnchantment","abstract fun addEnchantment(enchantment: Enchantment, level: Int): GuiButton","eu.xap3y.xagui.interfaces.GuiButtonInterface.addEnchantment"]},{"name":"abstract fun addItemFlag(flag: ItemFlag): GuiButton","description":"eu.xap3y.xagui.interfaces.GuiButtonInterface.addItemFlag","location":"-xa-gui/eu.xap3y.xagui.interfaces/-gui-button-interface/add-item-flag.html","searchKeys":["addItemFlag","abstract fun addItemFlag(flag: ItemFlag): GuiButton","eu.xap3y.xagui.interfaces.GuiButtonInterface.addItemFlag"]},{"name":"abstract fun clearAllSlots()","description":"eu.xap3y.xagui.interfaces.GuiInterface.clearAllSlots","location":"-xa-gui/eu.xap3y.xagui.interfaces/-gui-interface/clear-all-slots.html","searchKeys":["clearAllSlots","abstract fun clearAllSlots()","eu.xap3y.xagui.interfaces.GuiInterface.clearAllSlots"]},{"name":"abstract fun clearSlot(slot: Int)","description":"eu.xap3y.xagui.interfaces.GuiInterface.clearSlot","location":"-xa-gui/eu.xap3y.xagui.interfaces/-gui-interface/clear-slot.html","searchKeys":["clearSlot","abstract fun clearSlot(slot: Int)","eu.xap3y.xagui.interfaces.GuiInterface.clearSlot"]},{"name":"abstract fun close(player: Player)","description":"eu.xap3y.xagui.interfaces.GuiInterface.close","location":"-xa-gui/eu.xap3y.xagui.interfaces/-gui-interface/close.html","searchKeys":["close","abstract fun close(player: Player)","eu.xap3y.xagui.interfaces.GuiInterface.close"]},{"name":"abstract fun getIcon(): Material","description":"eu.xap3y.xagui.interfaces.GuiButtonInterface.getIcon","location":"-xa-gui/eu.xap3y.xagui.interfaces/-gui-button-interface/get-icon.html","searchKeys":["getIcon","abstract fun getIcon(): Material","eu.xap3y.xagui.interfaces.GuiButtonInterface.getIcon"]},{"name":"abstract fun getItem(): ItemStack","description":"eu.xap3y.xagui.interfaces.GuiButtonInterface.getItem","location":"-xa-gui/eu.xap3y.xagui.interfaces/-gui-button-interface/get-item.html","searchKeys":["getItem","abstract fun getItem(): ItemStack","eu.xap3y.xagui.interfaces.GuiButtonInterface.getItem"]},{"name":"abstract fun getName(): String","description":"eu.xap3y.xagui.interfaces.GuiInterface.getName","location":"-xa-gui/eu.xap3y.xagui.interfaces/-gui-interface/get-name.html","searchKeys":["getName","abstract fun getName(): String","eu.xap3y.xagui.interfaces.GuiInterface.getName"]},{"name":"abstract fun getOwner(): JavaPlugin","description":"eu.xap3y.xagui.interfaces.GuiInterface.getOwner","location":"-xa-gui/eu.xap3y.xagui.interfaces/-gui-interface/get-owner.html","searchKeys":["getOwner","abstract fun getOwner(): JavaPlugin","eu.xap3y.xagui.interfaces.GuiInterface.getOwner"]},{"name":"abstract fun getRawName(): String","description":"eu.xap3y.xagui.interfaces.GuiInterface.getRawName","location":"-xa-gui/eu.xap3y.xagui.interfaces/-gui-interface/get-raw-name.html","searchKeys":["getRawName","abstract fun getRawName(): String","eu.xap3y.xagui.interfaces.GuiInterface.getRawName"]},{"name":"abstract fun getSize(): Int","description":"eu.xap3y.xagui.interfaces.GuiInterface.getSize","location":"-xa-gui/eu.xap3y.xagui.interfaces/-gui-interface/get-size.html","searchKeys":["getSize","abstract fun getSize(): Int","eu.xap3y.xagui.interfaces.GuiInterface.getSize"]},{"name":"abstract fun getSlot(slot: Int): GuiButtonInterface?","description":"eu.xap3y.xagui.interfaces.GuiInterface.getSlot","location":"-xa-gui/eu.xap3y.xagui.interfaces/-gui-interface/get-slot.html","searchKeys":["getSlot","abstract fun getSlot(slot: Int): GuiButtonInterface?","eu.xap3y.xagui.interfaces.GuiInterface.getSlot"]},{"name":"abstract fun lockButton(slot: Int)","description":"eu.xap3y.xagui.interfaces.GuiInterface.lockButton","location":"-xa-gui/eu.xap3y.xagui.interfaces/-gui-interface/lock-button.html","searchKeys":["lockButton","abstract fun lockButton(slot: Int)","eu.xap3y.xagui.interfaces.GuiInterface.lockButton"]},{"name":"abstract fun onClick(event: InventoryClickEvent)","description":"eu.xap3y.xagui.interfaces.ButtonListener.onClick","location":"-xa-gui/eu.xap3y.xagui.interfaces/-button-listener/on-click.html","searchKeys":["onClick","abstract fun onClick(event: InventoryClickEvent)","eu.xap3y.xagui.interfaces.ButtonListener.onClick"]},{"name":"abstract fun onClick(event: InventoryClickEvent)","description":"eu.xap3y.xagui.interfaces.GuiClickInterface.onClick","location":"-xa-gui/eu.xap3y.xagui.interfaces/-gui-click-interface/on-click.html","searchKeys":["onClick","abstract fun onClick(event: InventoryClickEvent)","eu.xap3y.xagui.interfaces.GuiClickInterface.onClick"]},{"name":"abstract fun onClose(event: InventoryCloseEvent)","description":"eu.xap3y.xagui.interfaces.GuiCloseInterface.onClose","location":"-xa-gui/eu.xap3y.xagui.interfaces/-gui-close-interface/on-close.html","searchKeys":["onClose","abstract fun onClose(event: InventoryCloseEvent)","eu.xap3y.xagui.interfaces.GuiCloseInterface.onClose"]},{"name":"abstract fun onOpen(event: InventoryOpenEvent)","description":"eu.xap3y.xagui.interfaces.GuiOpenInterface.onOpen","location":"-xa-gui/eu.xap3y.xagui.interfaces/-gui-open-interface/on-open.html","searchKeys":["onOpen","abstract fun onOpen(event: InventoryOpenEvent)","eu.xap3y.xagui.interfaces.GuiOpenInterface.onOpen"]},{"name":"abstract fun open(player: Player)","description":"eu.xap3y.xagui.interfaces.GuiInterface.open","location":"-xa-gui/eu.xap3y.xagui.interfaces/-gui-interface/open.html","searchKeys":["open","abstract fun open(player: Player)","eu.xap3y.xagui.interfaces.GuiInterface.open"]},{"name":"abstract fun removeAllEnchantments(): GuiButton","description":"eu.xap3y.xagui.interfaces.GuiButtonInterface.removeAllEnchantments","location":"-xa-gui/eu.xap3y.xagui.interfaces/-gui-button-interface/remove-all-enchantments.html","searchKeys":["removeAllEnchantments","abstract fun removeAllEnchantments(): GuiButton","eu.xap3y.xagui.interfaces.GuiButtonInterface.removeAllEnchantments"]},{"name":"abstract fun removeEnchantment(enchantment: Enchantment): GuiButton","description":"eu.xap3y.xagui.interfaces.GuiButtonInterface.removeEnchantment","location":"-xa-gui/eu.xap3y.xagui.interfaces/-gui-button-interface/remove-enchantment.html","searchKeys":["removeEnchantment","abstract fun removeEnchantment(enchantment: Enchantment): GuiButton","eu.xap3y.xagui.interfaces.GuiButtonInterface.removeEnchantment"]},{"name":"abstract fun removeItemFlag(flag: ItemFlag): GuiButton","description":"eu.xap3y.xagui.interfaces.GuiButtonInterface.removeItemFlag","location":"-xa-gui/eu.xap3y.xagui.interfaces/-gui-button-interface/remove-item-flag.html","searchKeys":["removeItemFlag","abstract fun removeItemFlag(flag: ItemFlag): GuiButton","eu.xap3y.xagui.interfaces.GuiButtonInterface.removeItemFlag"]},{"name":"abstract fun setAmount(amount: Int): GuiButton","description":"eu.xap3y.xagui.interfaces.GuiButtonInterface.setAmount","location":"-xa-gui/eu.xap3y.xagui.interfaces/-gui-button-interface/set-amount.html","searchKeys":["setAmount","abstract fun setAmount(amount: Int): GuiButton","eu.xap3y.xagui.interfaces.GuiButtonInterface.setAmount"]},{"name":"abstract fun setDurability(durability: Short): GuiButton","description":"eu.xap3y.xagui.interfaces.GuiButtonInterface.setDurability","location":"-xa-gui/eu.xap3y.xagui.interfaces/-gui-button-interface/set-durability.html","searchKeys":["setDurability","abstract fun setDurability(durability: Short): GuiButton","eu.xap3y.xagui.interfaces.GuiButtonInterface.setDurability"]},{"name":"abstract fun setItem(item: ItemStack)","description":"eu.xap3y.xagui.interfaces.GuiButtonInterface.setItem","location":"-xa-gui/eu.xap3y.xagui.interfaces/-gui-button-interface/set-item.html","searchKeys":["setItem","abstract fun setItem(item: ItemStack)","eu.xap3y.xagui.interfaces.GuiButtonInterface.setItem"]},{"name":"abstract fun setLore(newLore: List<String>): GuiButton","description":"eu.xap3y.xagui.interfaces.GuiButtonInterface.setLore","location":"-xa-gui/eu.xap3y.xagui.interfaces/-gui-button-interface/set-lore.html","searchKeys":["setLore","abstract fun setLore(newLore: List<String>): GuiButton","eu.xap3y.xagui.interfaces.GuiButtonInterface.setLore"]},{"name":"abstract fun setName(name: String): GuiButton","description":"eu.xap3y.xagui.interfaces.GuiButtonInterface.setName","location":"-xa-gui/eu.xap3y.xagui.interfaces/-gui-button-interface/set-name.html","searchKeys":["setName","abstract fun setName(name: String): GuiButton","eu.xap3y.xagui.interfaces.GuiButtonInterface.setName"]},{"name":"abstract fun setName(newName: String)","description":"eu.xap3y.xagui.interfaces.GuiInterface.setName","location":"-xa-gui/eu.xap3y.xagui.interfaces/-gui-interface/set-name.html","searchKeys":["setName","abstract fun setName(newName: String)","eu.xap3y.xagui.interfaces.GuiInterface.setName"]},{"name":"abstract fun setOnClick(onClick: (InventoryClickEvent) -> Unit)","description":"eu.xap3y.xagui.interfaces.GuiInterface.setOnClick","location":"-xa-gui/eu.xap3y.xagui.interfaces/-gui-interface/set-on-click.html","searchKeys":["setOnClick","abstract fun setOnClick(onClick: (InventoryClickEvent) -> Unit)","eu.xap3y.xagui.interfaces.GuiInterface.setOnClick"]},{"name":"abstract fun setOnClose(closeAction: (InventoryCloseEvent) -> Unit)","description":"eu.xap3y.xagui.interfaces.GuiInterface.setOnClose","location":"-xa-gui/eu.xap3y.xagui.interfaces/-gui-interface/set-on-close.html","searchKeys":["setOnClose","abstract fun setOnClose(closeAction: (InventoryCloseEvent) -> Unit)","eu.xap3y.xagui.interfaces.GuiInterface.setOnClose"]},{"name":"abstract fun setOnOpen(openAction: (InventoryOpenEvent) -> Unit)","description":"eu.xap3y.xagui.interfaces.GuiInterface.setOnOpen","location":"-xa-gui/eu.xap3y.xagui.interfaces/-gui-interface/set-on-open.html","searchKeys":["setOnOpen","abstract fun setOnOpen(openAction: (InventoryOpenEvent) -> Unit)","eu.xap3y.xagui.interfaces.GuiInterface.setOnOpen"]},{"name":"abstract fun setSlot(slot: Int, button: GuiButtonInterface)","description":"eu.xap3y.xagui.interfaces.GuiInterface.setSlot","location":"-xa-gui/eu.xap3y.xagui.interfaces/-gui-interface/set-slot.html","searchKeys":["setSlot","abstract fun setSlot(slot: Int, button: GuiButtonInterface)","eu.xap3y.xagui.interfaces.GuiInterface.setSlot"]},{"name":"abstract fun unlockButton(slot: Int)","description":"eu.xap3y.xagui.interfaces.GuiInterface.unlockButton","location":"-xa-gui/eu.xap3y.xagui.interfaces/-gui-interface/unlock-button.html","searchKeys":["unlockButton","abstract fun unlockButton(slot: Int)","eu.xap3y.xagui.interfaces.GuiInterface.unlockButton"]},{"name":"abstract fun updateSlot(slot: Int, item: ItemStack)","description":"eu.xap3y.xagui.interfaces.GuiInterface.updateSlot","location":"-xa-gui/eu.xap3y.xagui.interfaces/-gui-interface/update-slot.html","searchKeys":["updateSlot","abstract fun updateSlot(slot: Int, item: ItemStack)","eu.xap3y.xagui.interfaces.GuiInterface.updateSlot"]},{"name":"abstract fun withListener(newListener: (InventoryClickEvent) -> Unit): GuiButton","description":"eu.xap3y.xagui.interfaces.GuiButtonInterface.withListener","location":"-xa-gui/eu.xap3y.xagui.interfaces/-gui-button-interface/with-listener.html","searchKeys":["withListener","abstract fun withListener(newListener: (InventoryClickEvent) -> Unit): GuiButton","eu.xap3y.xagui.interfaces.GuiButtonInterface.withListener"]},{"name":"abstract var listener: ButtonListener?","description":"eu.xap3y.xagui.interfaces.GuiButtonInterface.listener","location":"-xa-gui/eu.xap3y.xagui.interfaces/-gui-button-interface/listener.html","searchKeys":["listener","abstract var listener: ButtonListener?","eu.xap3y.xagui.interfaces.GuiButtonInterface.listener"]},{"name":"class GuiButton(item: ItemStack) : GuiButtonInterface","description":"eu.xap3y.xagui.models.GuiButton","location":"-xa-gui/eu.xap3y.xagui.models/-gui-button/index.html","searchKeys":["GuiButton","class GuiButton(item: ItemStack) : GuiButtonInterface","eu.xap3y.xagui.models.GuiButton"]},{"name":"class GuiMenu(plugin: JavaPlugin, title: String, rowsToSet: Int) : InventoryHolder, GuiInterface","description":"eu.xap3y.xagui.GuiMenu","location":"-xa-gui/eu.xap3y.xagui/-gui-menu/index.html","searchKeys":["GuiMenu","class GuiMenu(plugin: JavaPlugin, title: String, rowsToSet: Int) : InventoryHolder, GuiInterface","eu.xap3y.xagui.GuiMenu"]},{"name":"class GuiMenuListener(plugin: JavaPlugin) : Listener","description":"eu.xap3y.xagui.listeners.GuiMenuListener","location":"-xa-gui/eu.xap3y.xagui.listeners/-gui-menu-listener/index.html","searchKeys":["GuiMenuListener","class GuiMenuListener(plugin: JavaPlugin) : Listener","eu.xap3y.xagui.listeners.GuiMenuListener"]},{"name":"class RowsOutOfBoundException : Exception","description":"eu.xap3y.xagui.exceptions.RowsOutOfBoundException","location":"-xa-gui/eu.xap3y.xagui.exceptions/-rows-out-of-bound-exception/index.html","searchKeys":["RowsOutOfBoundException","class RowsOutOfBoundException : Exception","eu.xap3y.xagui.exceptions.RowsOutOfBoundException"]},{"name":"class SlotOutOfBoundException : Exception","description":"eu.xap3y.xagui.exceptions.SlotOutOfBoundException","location":"-xa-gui/eu.xap3y.xagui.exceptions/-slot-out-of-bound-exception/index.html","searchKeys":["SlotOutOfBoundException","class SlotOutOfBoundException : Exception","eu.xap3y.xagui.exceptions.SlotOutOfBoundException"]},{"name":"class XaGui(plugin: JavaPlugin)","description":"eu.xap3y.xagui.XaGui","location":"-xa-gui/eu.xap3y.xagui/-xa-gui/index.html","searchKeys":["XaGui","class XaGui(plugin: JavaPlugin)","eu.xap3y.xagui.XaGui"]},{"name":"constructor()","description":"eu.xap3y.xagui.exceptions.RowsOutOfBoundException.RowsOutOfBoundException","location":"-xa-gui/eu.xap3y.xagui.exceptions/-rows-out-of-bound-exception/-rows-out-of-bound-exception.html","searchKeys":["RowsOutOfBoundException","constructor()","eu.xap3y.xagui.exceptions.RowsOutOfBoundException.RowsOutOfBoundException"]},{"name":"constructor()","description":"eu.xap3y.xagui.exceptions.SlotOutOfBoundException.SlotOutOfBoundException","location":"-xa-gui/eu.xap3y.xagui.exceptions/-slot-out-of-bound-exception/-slot-out-of-bound-exception.html","searchKeys":["SlotOutOfBoundException","constructor()","eu.xap3y.xagui.exceptions.SlotOutOfBoundException.SlotOutOfBoundException"]},{"name":"constructor(item: ItemStack)","description":"eu.xap3y.xagui.models.GuiButton.GuiButton","location":"-xa-gui/eu.xap3y.xagui.models/-gui-button/-gui-button.html","searchKeys":["GuiButton","constructor(item: ItemStack)","eu.xap3y.xagui.models.GuiButton.GuiButton"]},{"name":"constructor(plugin: JavaPlugin)","description":"eu.xap3y.xagui.XaGui.XaGui","location":"-xa-gui/eu.xap3y.xagui/-xa-gui/-xa-gui.html","searchKeys":["XaGui","constructor(plugin: JavaPlugin)","eu.xap3y.xagui.XaGui.XaGui"]},{"name":"constructor(plugin: JavaPlugin)","description":"eu.xap3y.xagui.listeners.GuiMenuListener.GuiMenuListener","location":"-xa-gui/eu.xap3y.xagui.listeners/-gui-menu-listener/-gui-menu-listener.html","searchKeys":["GuiMenuListener","constructor(plugin: JavaPlugin)","eu.xap3y.xagui.listeners.GuiMenuListener.GuiMenuListener"]},{"name":"constructor(plugin: JavaPlugin, title: String, rowsToSet: Int)","description":"eu.xap3y.xagui.GuiMenu.GuiMenu","location":"-xa-gui/eu.xap3y.xagui/-gui-menu/-gui-menu.html","searchKeys":["GuiMenu","constructor(plugin: JavaPlugin, title: String, rowsToSet: Int)","eu.xap3y.xagui.GuiMenu.GuiMenu"]},{"name":"fun createMenu(name: String, rows: Int): GuiMenu","description":"eu.xap3y.xagui.XaGui.createMenu","location":"-xa-gui/eu.xap3y.xagui/-xa-gui/create-menu.html","searchKeys":["createMenu","fun createMenu(name: String, rows: Int): GuiMenu","eu.xap3y.xagui.XaGui.createMenu"]},{"name":"fun fillBorder(rows: Int)","description":"eu.xap3y.xagui.GuiMenu.fillBorder","location":"-xa-gui/eu.xap3y.xagui/-gui-menu/fill-border.html","searchKeys":["fillBorder","fun fillBorder(rows: Int)","eu.xap3y.xagui.GuiMenu.fillBorder"]},{"name":"fun fillBorder(rows: Int, item: ItemStack)","description":"eu.xap3y.xagui.GuiMenu.fillBorder","location":"-xa-gui/eu.xap3y.xagui/-gui-menu/fill-border.html","searchKeys":["fillBorder","fun fillBorder(rows: Int, item: ItemStack)","eu.xap3y.xagui.GuiMenu.fillBorder"]},{"name":"fun fillSlots(slots: Set<Int>, item: GuiButtonInterface = GuiButton(ItemStack(Material.GRAY_STAINED_GLASS_PANE).apply { itemMeta = itemMeta.apply { setDisplayName(\" \") }}))","description":"eu.xap3y.xagui.GuiMenu.fillSlots","location":"-xa-gui/eu.xap3y.xagui/-gui-menu/fill-slots.html","searchKeys":["fillSlots","fun fillSlots(slots: Set<Int>, item: GuiButtonInterface = GuiButton(ItemStack(Material.GRAY_STAINED_GLASS_PANE).apply { itemMeta = itemMeta.apply { setDisplayName(\" \") }}))","eu.xap3y.xagui.GuiMenu.fillSlots"]},{"name":"fun fillSlots(slots: Set<Int>, item: ItemStack = ItemStack(Material.GRAY_STAINED_GLASS_PANE).apply { itemMeta = itemMeta.apply { setDisplayName(\" \") }})","description":"eu.xap3y.xagui.GuiMenu.fillSlots","location":"-xa-gui/eu.xap3y.xagui/-gui-menu/fill-slots.html","searchKeys":["fillSlots","fun fillSlots(slots: Set<Int>, item: ItemStack = ItemStack(Material.GRAY_STAINED_GLASS_PANE).apply { itemMeta = itemMeta.apply { setDisplayName(\" \") }})","eu.xap3y.xagui.GuiMenu.fillSlots"]},{"name":"fun onInventoryClick(e: InventoryClickEvent)","description":"eu.xap3y.xagui.listeners.GuiMenuListener.onInventoryClick","location":"-xa-gui/eu.xap3y.xagui.listeners/-gui-menu-listener/on-inventory-click.html","searchKeys":["onInventoryClick","fun onInventoryClick(e: InventoryClickEvent)","eu.xap3y.xagui.listeners.GuiMenuListener.onInventoryClick"]},{"name":"fun onInventoryClose(e: InventoryCloseEvent)","description":"eu.xap3y.xagui.listeners.GuiMenuListener.onInventoryClose","location":"-xa-gui/eu.xap3y.xagui.listeners/-gui-menu-listener/on-inventory-close.html","searchKeys":["onInventoryClose","fun onInventoryClose(e: InventoryCloseEvent)","eu.xap3y.xagui.listeners.GuiMenuListener.onInventoryClose"]},{"name":"fun onInventoryOpen(e: InventoryOpenEvent)","description":"eu.xap3y.xagui.listeners.GuiMenuListener.onInventoryOpen","location":"-xa-gui/eu.xap3y.xagui.listeners/-gui-menu-listener/on-inventory-open.html","searchKeys":["onInventoryOpen","fun onInventoryOpen(e: InventoryOpenEvent)","eu.xap3y.xagui.listeners.GuiMenuListener.onInventoryOpen"]},{"name":"fun setSlot(slot: Int, item: ItemStack)","description":"eu.xap3y.xagui.GuiMenu.setSlot","location":"-xa-gui/eu.xap3y.xagui/-gui-menu/set-slot.html","searchKeys":["setSlot","fun setSlot(slot: Int, item: ItemStack)","eu.xap3y.xagui.GuiMenu.setSlot"]},{"name":"interface ButtonListener","description":"eu.xap3y.xagui.interfaces.ButtonListener","location":"-xa-gui/eu.xap3y.xagui.interfaces/-button-listener/index.html","searchKeys":["ButtonListener","interface ButtonListener","eu.xap3y.xagui.interfaces.ButtonListener"]},{"name":"interface GuiButtonInterface","description":"eu.xap3y.xagui.interfaces.GuiButtonInterface","location":"-xa-gui/eu.xap3y.xagui.interfaces/-gui-button-interface/index.html","searchKeys":["GuiButtonInterface","interface GuiButtonInterface","eu.xap3y.xagui.interfaces.GuiButtonInterface"]},{"name":"interface GuiClickInterface","description":"eu.xap3y.xagui.interfaces.GuiClickInterface","location":"-xa-gui/eu.xap3y.xagui.interfaces/-gui-click-interface/index.html","searchKeys":["GuiClickInterface","interface GuiClickInterface","eu.xap3y.xagui.interfaces.GuiClickInterface"]},{"name":"interface GuiCloseInterface","description":"eu.xap3y.xagui.interfaces.GuiCloseInterface","location":"-xa-gui/eu.xap3y.xagui.interfaces/-gui-close-interface/index.html","searchKeys":["GuiCloseInterface","interface GuiCloseInterface","eu.xap3y.xagui.interfaces.GuiCloseInterface"]},{"name":"interface GuiInterface","description":"eu.xap3y.xagui.interfaces.GuiInterface","location":"-xa-gui/eu.xap3y.xagui.interfaces/-gui-interface/index.html","searchKeys":["GuiInterface","interface GuiInterface","eu.xap3y.xagui.interfaces.GuiInterface"]},{"name":"interface GuiOpenInterface","description":"eu.xap3y.xagui.interfaces.GuiOpenInterface","location":"-xa-gui/eu.xap3y.xagui.interfaces/-gui-open-interface/index.html","searchKeys":["GuiOpenInterface","interface GuiOpenInterface","eu.xap3y.xagui.interfaces.GuiOpenInterface"]},{"name":"open override fun addEnchantment(enchantment: Enchantment): GuiButton","description":"eu.xap3y.xagui.models.GuiButton.addEnchantment","location":"-xa-gui/eu.xap3y.xagui.models/-gui-button/add-enchantment.html","searchKeys":["addEnchantment","open override fun addEnchantment(enchantment: Enchantment): GuiButton","eu.xap3y.xagui.models.GuiButton.addEnchantment"]},{"name":"open override fun addEnchantment(enchantment: Enchantment, level: Int): GuiButton","description":"eu.xap3y.xagui.models.GuiButton.addEnchantment","location":"-xa-gui/eu.xap3y.xagui.models/-gui-button/add-enchantment.html","searchKeys":["addEnchantment","open override fun addEnchantment(enchantment: Enchantment, level: Int): GuiButton","eu.xap3y.xagui.models.GuiButton.addEnchantment"]},{"name":"open override fun addItemFlag(flag: ItemFlag): GuiButton","description":"eu.xap3y.xagui.models.GuiButton.addItemFlag","location":"-xa-gui/eu.xap3y.xagui.models/-gui-button/add-item-flag.html","searchKeys":["addItemFlag","open override fun addItemFlag(flag: ItemFlag): GuiButton","eu.xap3y.xagui.models.GuiButton.addItemFlag"]},{"name":"open override fun clearAllSlots()","description":"eu.xap3y.xagui.GuiMenu.clearAllSlots","location":"-xa-gui/eu.xap3y.xagui/-gui-menu/clear-all-slots.html","searchKeys":["clearAllSlots","open override fun clearAllSlots()","eu.xap3y.xagui.GuiMenu.clearAllSlots"]},{"name":"open override fun clearSlot(slot: Int)","description":"eu.xap3y.xagui.GuiMenu.clearSlot","location":"-xa-gui/eu.xap3y.xagui/-gui-menu/clear-slot.html","searchKeys":["clearSlot","open override fun clearSlot(slot: Int)","eu.xap3y.xagui.GuiMenu.clearSlot"]},{"name":"open override fun close(player: Player)","description":"eu.xap3y.xagui.GuiMenu.close","location":"-xa-gui/eu.xap3y.xagui/-gui-menu/close.html","searchKeys":["close","open override fun close(player: Player)","eu.xap3y.xagui.GuiMenu.close"]},{"name":"open override fun getIcon(): Material","description":"eu.xap3y.xagui.models.GuiButton.getIcon","location":"-xa-gui/eu.xap3y.xagui.models/-gui-button/get-icon.html","searchKeys":["getIcon","open override fun getIcon(): Material","eu.xap3y.xagui.models.GuiButton.getIcon"]},{"name":"open override fun getInventory(): Inventory","description":"eu.xap3y.xagui.GuiMenu.getInventory","location":"-xa-gui/eu.xap3y.xagui/-gui-menu/get-inventory.html","searchKeys":["getInventory","open override fun getInventory(): Inventory","eu.xap3y.xagui.GuiMenu.getInventory"]},{"name":"open override fun getItem(): ItemStack","description":"eu.xap3y.xagui.models.GuiButton.getItem","location":"-xa-gui/eu.xap3y.xagui.models/-gui-button/get-item.html","searchKeys":["getItem","open override fun getItem(): ItemStack","eu.xap3y.xagui.models.GuiButton.getItem"]},{"name":"open override fun getName(): String","description":"eu.xap3y.xagui.GuiMenu.getName","location":"-xa-gui/eu.xap3y.xagui/-gui-menu/get-name.html","searchKeys":["getName","open override fun getName(): String","eu.xap3y.xagui.GuiMenu.getName"]},{"name":"open override fun getOwner(): JavaPlugin","description":"eu.xap3y.xagui.GuiMenu.getOwner","location":"-xa-gui/eu.xap3y.xagui/-gui-menu/get-owner.html","searchKeys":["getOwner","open override fun getOwner(): JavaPlugin","eu.xap3y.xagui.GuiMenu.getOwner"]},{"name":"open override fun getRawName(): String","description":"eu.xap3y.xagui.GuiMenu.getRawName","location":"-xa-gui/eu.xap3y.xagui/-gui-menu/get-raw-name.html","searchKeys":["getRawName","open override fun getRawName(): String","eu.xap3y.xagui.GuiMenu.getRawName"]},{"name":"open override fun getSize(): Int","description":"eu.xap3y.xagui.GuiMenu.getSize","location":"-xa-gui/eu.xap3y.xagui/-gui-menu/get-size.html","searchKeys":["getSize","open override fun getSize(): Int","eu.xap3y.xagui.GuiMenu.getSize"]},{"name":"open override fun getSlot(slot: Int): GuiButtonInterface?","description":"eu.xap3y.xagui.GuiMenu.getSlot","location":"-xa-gui/eu.xap3y.xagui/-gui-menu/get-slot.html","searchKeys":["getSlot","open override fun getSlot(slot: Int): GuiButtonInterface?","eu.xap3y.xagui.GuiMenu.getSlot"]},{"name":"open override fun lockButton(slot: Int)","description":"eu.xap3y.xagui.GuiMenu.lockButton","location":"-xa-gui/eu.xap3y.xagui/-gui-menu/lock-button.html","searchKeys":["lockButton","open override fun lockButton(slot: Int)","eu.xap3y.xagui.GuiMenu.lockButton"]},{"name":"open override fun open(player: Player)","description":"eu.xap3y.xagui.GuiMenu.open","location":"-xa-gui/eu.xap3y.xagui/-gui-menu/open.html","searchKeys":["open","open override fun open(player: Player)","eu.xap3y.xagui.GuiMenu.open"]},{"name":"open override fun removeAllEnchantments(): GuiButton","description":"eu.xap3y.xagui.models.GuiButton.removeAllEnchantments","location":"-xa-gui/eu.xap3y.xagui.models/-gui-button/remove-all-enchantments.html","searchKeys":["removeAllEnchantments","open override fun removeAllEnchantments(): GuiButton","eu.xap3y.xagui.models.GuiButton.removeAllEnchantments"]},{"name":"open override fun removeEnchantment(enchantment: Enchantment): GuiButton","description":"eu.xap3y.xagui.models.GuiButton.removeEnchantment","location":"-xa-gui/eu.xap3y.xagui.models/-gui-button/remove-enchantment.html","searchKeys":["removeEnchantment","open override fun removeEnchantment(enchantment: Enchantment): GuiButton","eu.xap3y.xagui.models.GuiButton.removeEnchantment"]},{"name":"open override fun removeItemFlag(flag: ItemFlag): GuiButton","description":"eu.xap3y.xagui.models.GuiButton.removeItemFlag","location":"-xa-gui/eu.xap3y.xagui.models/-gui-button/remove-item-flag.html","searchKeys":["removeItemFlag","open override fun removeItemFlag(flag: ItemFlag): GuiButton","eu.xap3y.xagui.models.GuiButton.removeItemFlag"]},{"name":"open override fun setAmount(amount: Int): GuiButton","description":"eu.xap3y.xagui.models.GuiButton.setAmount","location":"-xa-gui/eu.xap3y.xagui.models/-gui-button/set-amount.html","searchKeys":["setAmount","open override fun setAmount(amount: Int): GuiButton","eu.xap3y.xagui.models.GuiButton.setAmount"]},{"name":"open override fun setDurability(durability: Short): GuiButton","description":"eu.xap3y.xagui.models.GuiButton.setDurability","location":"-xa-gui/eu.xap3y.xagui.models/-gui-button/set-durability.html","searchKeys":["setDurability","open override fun setDurability(durability: Short): GuiButton","eu.xap3y.xagui.models.GuiButton.setDurability"]},{"name":"open override fun setItem(item: ItemStack)","description":"eu.xap3y.xagui.models.GuiButton.setItem","location":"-xa-gui/eu.xap3y.xagui.models/-gui-button/set-item.html","searchKeys":["setItem","open override fun setItem(item: ItemStack)","eu.xap3y.xagui.models.GuiButton.setItem"]},{"name":"open override fun setLore(newLore: List<String>): GuiButton","description":"eu.xap3y.xagui.models.GuiButton.setLore","location":"-xa-gui/eu.xap3y.xagui.models/-gui-button/set-lore.html","searchKeys":["setLore","open override fun setLore(newLore: List<String>): GuiButton","eu.xap3y.xagui.models.GuiButton.setLore"]},{"name":"open override fun setName(name: String): GuiButton","description":"eu.xap3y.xagui.models.GuiButton.setName","location":"-xa-gui/eu.xap3y.xagui.models/-gui-button/set-name.html","searchKeys":["setName","open override fun setName(name: String): GuiButton","eu.xap3y.xagui.models.GuiButton.setName"]},{"name":"open override fun setName(newName: String)","description":"eu.xap3y.xagui.GuiMenu.setName","location":"-xa-gui/eu.xap3y.xagui/-gui-menu/set-name.html","searchKeys":["setName","open override fun setName(newName: String)","eu.xap3y.xagui.GuiMenu.setName"]},{"name":"open override fun setOnClick(onClick: (InventoryClickEvent) -> Unit)","description":"eu.xap3y.xagui.GuiMenu.setOnClick","location":"-xa-gui/eu.xap3y.xagui/-gui-menu/set-on-click.html","searchKeys":["setOnClick","open override fun setOnClick(onClick: (InventoryClickEvent) -> Unit)","eu.xap3y.xagui.GuiMenu.setOnClick"]},{"name":"open override fun setOnClose(closeAction: (InventoryCloseEvent) -> Unit)","description":"eu.xap3y.xagui.GuiMenu.setOnClose","location":"-xa-gui/eu.xap3y.xagui/-gui-menu/set-on-close.html","searchKeys":["setOnClose","open override fun setOnClose(closeAction: (InventoryCloseEvent) -> Unit)","eu.xap3y.xagui.GuiMenu.setOnClose"]},{"name":"open override fun setOnOpen(openAction: (InventoryOpenEvent) -> Unit)","description":"eu.xap3y.xagui.GuiMenu.setOnOpen","location":"-xa-gui/eu.xap3y.xagui/-gui-menu/set-on-open.html","searchKeys":["setOnOpen","open override fun setOnOpen(openAction: (InventoryOpenEvent) -> Unit)","eu.xap3y.xagui.GuiMenu.setOnOpen"]},{"name":"open override fun setSlot(slot: Int, button: GuiButtonInterface)","description":"eu.xap3y.xagui.GuiMenu.setSlot","location":"-xa-gui/eu.xap3y.xagui/-gui-menu/set-slot.html","searchKeys":["setSlot","open override fun setSlot(slot: Int, button: GuiButtonInterface)","eu.xap3y.xagui.GuiMenu.setSlot"]},{"name":"open override fun unlockButton(slot: Int)","description":"eu.xap3y.xagui.GuiMenu.unlockButton","location":"-xa-gui/eu.xap3y.xagui/-gui-menu/unlock-button.html","searchKeys":["unlockButton","open override fun unlockButton(slot: Int)","eu.xap3y.xagui.GuiMenu.unlockButton"]},{"name":"open override fun updateSlot(slot: Int, item: ItemStack)","description":"eu.xap3y.xagui.GuiMenu.updateSlot","location":"-xa-gui/eu.xap3y.xagui/-gui-menu/update-slot.html","searchKeys":["updateSlot","open override fun updateSlot(slot: Int, item: ItemStack)","eu.xap3y.xagui.GuiMenu.updateSlot"]},{"name":"open override fun withListener(newListener: (InventoryClickEvent) -> Unit): GuiButton","description":"eu.xap3y.xagui.models.GuiButton.withListener","location":"-xa-gui/eu.xap3y.xagui.models/-gui-button/with-listener.html","searchKeys":["withListener","open override fun withListener(newListener: (InventoryClickEvent) -> Unit): GuiButton","eu.xap3y.xagui.models.GuiButton.withListener"]},{"name":"open override var listener: ButtonListener?","description":"eu.xap3y.xagui.models.GuiButton.listener","location":"-xa-gui/eu.xap3y.xagui.models/-gui-button/listener.html","searchKeys":["listener","open override var listener: ButtonListener?","eu.xap3y.xagui.models.GuiButton.listener"]},{"name":"val unlockedSlots: MutableSet<Int>","description":"eu.xap3y.xagui.GuiMenu.unlockedSlots","location":"-xa-gui/eu.xap3y.xagui/-gui-menu/unlocked-slots.html","searchKeys":["unlockedSlots","val unlockedSlots: MutableSet<Int>","eu.xap3y.xagui.GuiMenu.unlockedSlots"]},{"name":"var onClickAction: GuiClickInterface?","description":"eu.xap3y.xagui.GuiMenu.onClickAction","location":"-xa-gui/eu.xap3y.xagui/-gui-menu/on-click-action.html","searchKeys":["onClickAction","var onClickAction: GuiClickInterface?","eu.xap3y.xagui.GuiMenu.onClickAction"]},{"name":"var onCloseAction: GuiCloseInterface?","description":"eu.xap3y.xagui.GuiMenu.onCloseAction","location":"-xa-gui/eu.xap3y.xagui/-gui-menu/on-close-action.html","searchKeys":["onCloseAction","var onCloseAction: GuiCloseInterface?","eu.xap3y.xagui.GuiMenu.onCloseAction"]},{"name":"var onOpenAction: GuiOpenInterface?","description":"eu.xap3y.xagui.GuiMenu.onOpenAction","location":"-xa-gui/eu.xap3y.xagui/-gui-menu/on-open-action.html","searchKeys":["onOpenAction","var onOpenAction: GuiOpenInterface?","eu.xap3y.xagui.GuiMenu.onOpenAction"]}]
